LICENSE
MANIFEST.in
README.md
requirements.txt
setup.py
oxasl_enable/__init__.py
oxasl_enable/_version.py
oxasl_enable/enable.py
oxasl_enable/preproc.py
oxasl_enable.egg-info/PKG-INFO
oxasl_enable.egg-info/SOURCES.txt
oxasl_enable.egg-info/dependency_links.txt
oxasl_enable.egg-info/requires.txt
oxasl_enable.egg-info/top_level.txt